walsync-0.1.1.dist-info/METADATA
walsync-0.1.1.dist-info/WHEEL
walsync/__init__.py
walsync/walsync.cpython-312-darwin.so
walsync-0.1.1.dist-info/RECORD
