Metadata-Version: 2.4
Name: walsync
Version: 0.1.1
Classifier: Development Status :: 4 - Beta
Classifier: Intended Audience :: Developers
Classifier: License :: OSI Approved :: Apache Software License
Classifier: Programming Language :: Python :: 3
Classifier: Programming Language :: Python :: 3.8
Classifier: Programming Language :: Python :: 3.9
Classifier: Programming Language :: Python :: 3.10
Classifier: Programming Language :: Python :: 3.11
Classifier: Programming Language :: Python :: 3.12
Classifier: Programming Language :: Rust
Summary: Lightweight SQLite WAL sync to S3/Tigris
Keywords: sqlite,wal,s3,backup,sync,tigris
Author-email: Russell Romney <russellromney@gmail.com>
License: Apache-2.0
Requires-Python: >=3.8
Project-URL: Repository, https://github.com/russellromney/walsync
